Metadata-Version: 2.1
Name: yndx-parse
Version: 0.10
Summary: some descr
Home-page: https://github.com/FonDerMark/yndx-parse
Author: Xm0rph
Author-email: publicnox@gmail.com
License: MIT
License-File: LICENSE
